vikit/__init__.py
vikit/music_building_context.py
vikit/version.py
vikit/common/GeneralBuildSettings.py
vikit/common/__init__.py
vikit/common/config.py
vikit/common/context_managers.py
vikit/common/decorators.py
vikit/common/file_tools.py
vikit/common/handler.py
vikit/common/secrets.py
vikit/common/test_file_tools.py
vikit/gateways/ML_models_gateway.py
vikit/gateways/ML_models_gateway_factory.py
vikit/gateways/__init__.py
vikit/gateways/elevenlabs_gateway.py
vikit/gateways/fake_ML_models_gateway.py
vikit/gateways/replicate_gateway.py
vikit/gateways/vikit_gateway.py
vikit/postprocessing/__init__.py
vikit/postprocessing/video_subtitle_renderer.py
vikit/prompt/__init__.py
vikit/prompt/image_prompt.py
vikit/prompt/multimodal_prompt.py
vikit/prompt/prompt.py
vikit/prompt/prompt_build_settings.py
vikit/prompt/prompt_cleaning.py
vikit/prompt/prompt_factory.py
vikit/prompt/recorded_prompt.py
vikit/prompt/recorded_prompt_subtitles_extractor.py
vikit/prompt/subtitle_extractor.py
vikit/video/__init__.py
vikit/video/composite_video.py
vikit/video/imported_video.py
vikit/video/prompt_based_video.py
vikit/video/raw_image_based_video.py
vikit/video/raw_multimodal_based_video.py
vikit/video/raw_text_based_video.py
vikit/video/seine_transition.py
vikit/video/transition.py
vikit/video/video.py
vikit/video/video_build_history.py
vikit/video/video_build_settings.py
vikit/video/video_file_name.py
vikit/video/video_metadata.py
vikit/video/video_types.py
vikit/video/building/__init__.py
vikit/video/building/build_order.py
vikit/video/building/video_building_pipeline.py
vikit/video/building/handlers/__init__.py
vikit/video/building/handlers/default_bg_music_and_audio_merging_handler.py
vikit/video/building/handlers/gen_read_aloud_prompt_and_audio_merging_handler.py
vikit/video/building/handlers/generate_music_and_merge_handler.py
vikit/video/building/handlers/interpolation_handler.py
vikit/video/building/handlers/transition_handler.py
vikit_ai_sdk_dev-0.25.0.dist-info/LICENSE
vikit_ai_sdk_dev-0.25.0.dist-info/METADATA
vikit_ai_sdk_dev-0.25.0.dist-info/WHEEL
vikit_ai_sdk_dev-0.25.0.dist-info/top_level.txt
vikit_ai_sdk_dev-0.25.0.dist-info/RECORD
