Metadata-Version: 2.1
Name: vikit-ai-sdk-dev
Version: 0.25.0
Summary: Vikit.ai Software Development Kit
Home-page: https://github.com/vikit-ai/sdk
Author: Vikit.ai
Author-email: hello@vikit.ai
Classifier: Development Status :: 4 - Beta
Classifier: Intended Audience :: Developers
Classifier: Programming Language :: Python :: 3.8
Classifier: Programming Language :: Python :: 3.9
Classifier: Programming Language :: Python :: 3.10
Requires-Python: >=3.6
License-File: LICENSE
Requires-Dist: aiohttp>=3.8.0
Requires-Dist: aiofiles>=0.8.0
Requires-Dist: google-cloud-storage>=2.0.0
Requires-Dist: tenacity>=8.0.0
Requires-Dist: pytest>=7.0.0
Requires-Dist: pytest-asyncio>=0.18.0
Provides-Extra: dev
Requires-Dist: pytest; extra == "dev"
Requires-Dist: pytest-asyncio; extra == "dev"
Requires-Dist: pytest-cov; extra == "dev"
Requires-Dist: black; extra == "dev"
Requires-Dist: isort; extra == "dev"
Requires-Dist: flake8; extra == "dev"
Requires-Dist: wheel; extra == "dev"
